boot_prefect/__init__.py
boot_prefect/boot_prefect.py
boot_prefect-0.0.1.dist-info/LICENCE
boot_prefect-0.0.1.dist-info/METADATA
boot_prefect-0.0.1.dist-info/WHEEL
boot_prefect-0.0.1.dist-info/entry_points.txt
boot_prefect-0.0.1.dist-info/top_level.txt
boot_prefect-0.0.1.dist-info/RECORD
