Metadata-Version: 2.1
Name: boot_prefect
Version: 0.0.1
Summary: A simple CLI that shortcuts starting a local Prefect server and worker
Author-email: Christopher Marriott <christopher.marriott@nspcc.org.uk>
License: Copyright 2024 Christopher Marriott
Project-URL: homepage, https://github.com/nspcc-cm/boot_prefect
Project-URL: repository, https://github.com/nspcc-cm/boot_prefect.git
Classifier: Development Status :: 1 - Planning
Classifier: Intended Audience :: Developers
Classifier: License :: OSI Approved :: MIT License
Classifier: Programming Language :: Python :: 3
Classifier: Environment :: Console
License-File: LICENCE
Requires-Dist: click
